moray/__init__.py
moray/_checker.py
moray/_config.py
moray/_runner.py
moray/exception.py
moray/js.py
moray/_browser/__init__.py
moray/_browser/chrome.py
moray/_module/__init__.py
moray/_module/py/__init__.py
moray/_module/py/template/js_module.js
moray/_module/py/template/window_position.js
moray/_module/static/__init__.py
moray/_module/static/core.js
moray/_module/static/moray.js
moray/_server/__init__.py
moray-0.0.1.dist-info/LICENSE
moray-0.0.1.dist-info/METADATA
moray-0.0.1.dist-info/WHEEL
moray-0.0.1.dist-info/top_level.txt
moray-0.0.1.dist-info/RECORD
