Metadata-Version: 2.1
Name: moray
Version: 0.0.1
Summary: Package for creating HTML GUI using Python modules and JavaScript.
Home-page: https://github.com/hirorich/moray
Author: hirorich
License: UNKNOWN
Project-URL: Bug Tracker, https://github.com/hirorich/moray/issues
Keywords: gui,html,javascript
Platform: UNKNOWN
Classifier: Programming Language :: Python :: 3.9
Classifier: License :: OSI Approved :: MIT License
Classifier: Operating System :: Microsoft :: Windows :: Windows 10
Requires-Python: >=3.9
License-File: LICENSE
Requires-Dist: bottle-websocket
Requires-Dist: requests
Requires-Dist: Jinja2
